{
  "ret": true,
  "data": {
    "assets": {
      "assetsList": [
        {
          "assetName": "PC1",
          "IPAddress": "192.168.3.25",
          "MACAddress": "xxxxxxxx",
          "OperateSys": "PC1",
          "business": "业务网路1",
          "type": "高",
          "grade": "很高",
          "event": "xxxxxxx",
          "Vulnerability": "xxxxxxx",
          "port": "xxxx",
          "status": "xxxxxxx",
          "findTime": "2018-01-28 13:16:18",
          "operate": "xxxxx"
        },
        {
          "assetName": "PC1",
          "IPAddress": "192.168.3.25",
          "MACAddress": "xxxxxxxx",
          "OperateSys": "PC1",
          "business": "业务网路1",
          "type": "高",
          "grade": "很高",
          "event": "xxxxxxx",
          "Vulnerability": "xxxxxxx",
          "port": "xxxx",
          "status": "xxxxxxx",
          "findTime": "2018-01-28 13:16:18",
          "operate": "xxxxx"
        },
        {
          "assetName": "PC1",
          "IPAddress": "192.168.3.25",
          "MACAddress": "xxxxxxxx",
          "OperateSys": "PC1",
          "business": "业务网路1",
          "type": "高",
          "grade": "很高",
          "event": "xxxxxxx",
          "Vulnerability": "xxxxxxx",
          "port": "xxxx",
          "status": "xxxxxxx",
          "findTime": "2018-01-28 13:16:18",
          "operate": "xxxxx"
        },
        {
          "assetName": "PC1",
          "IPAddress": "192.168.3.25",
          "MACAddress": "xxxxxxxx",
          "OperateSys": "PC1",
          "business": "业务网路1",
          "type": "高",
          "grade": "很高",
          "event": "xxxxxxx",
          "Vulnerability": "xxxxxxx",
          "port": "xxxx",
          "status": "xxxxxxx",
          "findTime": "2018-01-28 13:16:18",
          "operate": "xxxxx"
        },
        {
          "assetName": "PC1",
          "IPAddress": "192.168.3.25",
          "MACAddress": "xxxxxxxx",
          "OperateSys": "PC1",
          "business": "业务网路1",
          "type": "高",
          "grade": "很高",
          "event": "xxxxxxx",
          "Vulnerability": "xxxxxxx",
          "port": "xxxx",
          "status": "xxxxxxx",
          "findTime": "2018-01-28 13:16:18",
          "operate": "xxxxx"
        },
        {
          "assetName": "PC1",
          "IPAddress": "192.168.3.25",
          "MACAddress": "xxxxxxxx",
          "OperateSys": "PC1",
          "business": "业务网路1",
          "type": "高",
          "grade": "很高",
          "event": "xxxxxxx",
          "Vulnerability": "xxxxxxx",
          "port": "xxxx",
          "status": "xxxxxxx",
          "findTime": "2018-01-28 13:16:18",
          "operate": "xxxxx"
        },
        {
          "assetName": "PC1",
          "IPAddress": "192.168.3.25",
          "MACAddress": "xxxxxxxx",
          "OperateSys": "PC1",
          "business": "业务网路1",
          "type": "高",
          "grade": "很高",
          "event": "xxxxxxx",
          "Vulnerability": "xxxxxxx",
          "port": "xxxx",
          "status": "xxxxxxx",
          "findTime": "2018-01-28 13:16:18",
          "operate": "xxxxx"
        },
        {
          "assetName": "PC1",
          "IPAddress": "192.168.3.25",
          "MACAddress": "xxxxxxxx",
          "OperateSys": "PC1",
          "business": "业务网路1",
          "type": "高",
          "grade": "很高",
          "event": "xxxxxxx",
          "Vulnerability": "xxxxxxx",
          "port": "xxxx",
          "status": "xxxxxxx",
          "findTime": "2018-01-28 13:16:18",
          "operate": "xxxxx"
        }
      ]
    },
    "events": {
      "eventData": [
        {
          "findTime": "2018-5-22 14:11:29",
          "eventName": "名称",
          "eventGrade": "重大",
          "eventType": "其他",
          "srcAdd": "xxx.xxx.xxx.xxx",
          "desAdd": "xxx.xxx.xxx.xxx",
          "status": "已确认",
          "detail": "xxxxxxx"
        },
        {
          "findTime": "2018-5-22 14:11:29",
          "eventName": "名称",
          "eventGrade": "重大",
          "eventType": "其他",
          "srcAdd": "xxx.xxx.xxx.xxx",
          "desAdd": "xxx.xxx.xxx.xxx",
          "status": "已确认",
          "detail": "xxxxxxx"
        },
        {
          "findTime": "2018-5-22 14:11:29",
          "eventName": "名称",
          "eventGrade": "重大",
          "eventType": "其他",
          "srcAdd": "xxx.xxx.xxx.xxx",
          "desAdd": "xxx.xxx.xxx.xxx",
          "status": "已确认",
          "detail": "xxxxxxx"
        },
        {
          "findTime": "2018-5-22 14:11:29",
          "eventName": "名称",
          "eventGrade": "重大",
          "eventType": "其他",
          "srcAdd": "xxx.xxx.xxx.xxx",
          "desAdd": "xxx.xxx.xxx.xxx",
          "status": "已确认",
          "detail": "xxxxxxx"
        },
        {
          "findTime": "2018-5-22 14:11:29",
          "eventName": "名称",
          "eventGrade": "重大",
          "eventType": "其他",
          "srcAdd": "xxx.xxx.xxx.xxx",
          "desAdd": "xxx.xxx.xxx.xxx",
          "status": "已确认",
          "detail": "xxxxxxx"
        },
        {
          "findTime": "2018-5-22 14:11:29",
          "eventName": "名称",
          "eventGrade": "重大",
          "eventType": "其他",
          "srcAdd": "xxx.xxx.xxx.xxx",
          "desAdd": "xxx.xxx.xxx.xxx",
          "status": "已确认",
          "detail": "xxxxxxx"
        },
        {
          "findTime": "2018-5-22 14:11:29",
          "eventName": "名称",
          "eventGrade": "重大",
          "eventType": "其他",
          "srcAdd": "xxx.xxx.xxx.xxx",
          "desAdd": "xxx.xxx.xxx.xxx",
          "status": "已确认",
          "detail": "xxxxxxx"
        },
        {
          "findTime": "2018-5-22 14:11:29",
          "eventName": "名称",
          "eventGrade": "重大",
          "eventType": "其他",
          "srcAdd": "xxx.xxx.xxx.xxx",
          "desAdd": "xxx.xxx.xxx.xxx",
          "status": "已确认",
          "detail": "xxxxxxx"
        },
        {
          "findTime": "2018-5-22 14:11:29",
          "eventName": "名称",
          "eventGrade": "重大",
          "eventType": "其他",
          "srcAdd": "xxx.xxx.xxx.xxx",
          "desAdd": "xxx.xxx.xxx.xxx",
          "status": "已确认",
          "detail": "xxxxxxx"
        }
      ]
    },
    "flows": {
      "sessRank": [
        {
          "srcName": "PC1",
          "srcAdd": "xxxxx",
          "desName": "PC2",
          "desAdd": "xxxxx",
          "appPro": "http",
          "flows": "256KB"
        },
        {
          "srcName": "PC1",
          "srcAdd": "xxxxx",
          "desName": "PC2",
          "desAdd": "xxxxx",
          "appPro": "http",
          "flows": "256KB"
        },
        {
          "srcName": "PC1",
          "srcAdd": "xxxxx",
          "desName": "PC2",
          "desAdd": "xxxxx",
          "appPro": "http",
          "flows": "256KB"
        },
        {
          "srcName": "PC1",
          "srcAdd": "xxxxx",
          "desName": "PC2",
          "desAdd": "xxxxx",
          "appPro": "http",
          "flows": "256KB"
        },
        {
          "srcName": "PC1",
          "srcAdd": "xxxxx",
          "desName": "PC2",
          "desAdd": "xxxxx",
          "appPro": "http",
          "flows": "256KB"
        },
        {
          "srcName": "PC1",
          "srcAdd": "xxxxx",
          "desName": "PC2",
          "desAdd": "xxxxx",
          "appPro": "http",
          "flows": "256KB"
        },
        {
          "srcName": "PC1",
          "srcAdd": "xxxxx",
          "desName": "PC2",
          "desAdd": "xxxxx",
          "appPro": "http",
          "flows": "256KB"
        },
        {
          "srcName": "PC1",
          "srcAdd": "xxxxx",
          "desName": "PC2",
          "desAdd": "xxxxx",
          "appPro": "http",
          "flows": "256KB"
        },
        {
          "srcName": "PC1",
          "srcAdd": "xxxxx",
          "desName": "PC2",
          "desAdd": "xxxxx",
          "appPro": "http",
          "flows": "256KB"
        },
        {
          "srcName": "PC1",
          "srcAdd": "xxxxx",
          "desName": "PC2",
          "desAdd": "xxxxx",
          "appPro": "http",
          "flows": "256KB"
        },
        {
          "srcName": "PC1",
          "srcAdd": "xxxxx",
          "desName": "PC2",
          "desAdd": "xxxxx",
          "appPro": "http",
          "flows": "256KB"
        },
        {
          "srcName": "PC1",
          "srcAdd": "xxxxx",
          "desName": "PC2",
          "desAdd": "xxxxx",
          "appPro": "http",
          "flows": "256KB"
        },
        {
          "srcName": "PC1",
          "srcAdd": "xxxxx",
          "desName": "PC2",
          "desAdd": "xxxxx",
          "appPro": "http",
          "flows": "256KB"
        },
        {
          "srcName": "PC1",
          "srcAdd": "xxxxx",
          "desName": "PC2",
          "desAdd": "xxxxx",
          "appPro": "http",
          "flows": "256KB"
        },
        {
          "srcName": "PC1",
          "srcAdd": "xxxxx",
          "desName": "PC2",
          "desAdd": "xxxxx",
          "appPro": "http",
          "flows": "256KB"
        }
      ],
      "sendSource":[
        {
          "sendIP":"192.2.15.161",
          "percent":"20%",
          "flow":"50KB"
        },
        {
          "sendIP":"192.2.15.161",
          "percent":"20%",
          "flow":"50KB"
        },
        {
          "sendIP":"192.2.15.161",
          "percent":"20%",
          "flow":"50KB"
        },
        {
          "sendIP":"192.2.15.161",
          "percent":"20%",
          "flow":"50KB"
        },
        {
          "sendIP":"192.2.15.161",
          "percent":"20%",
          "flow":"50KB"
        },
        {
          "sendIP":"192.2.15.161",
          "percent":"20%",
          "flow":"50KB"
        },
        {
          "sendIP":"192.2.15.161",
          "percent":"20%",
          "flow":"50KB"
        },
        {
          "sendIP":"192.2.15.161",
          "percent":"20%",
          "flow":"50KB"
        }
      ],
      "receiveSource": [
        {
          "receiveIP":"192.2.15.161",
          "percent":"20%",
          "flow":"50KB"
        },
        {
          "receiveIP":"192.2.15.161",
          "percent":"20%",
          "flow":"50KB"
        },
        {
          "receiveIP":"192.2.15.161",
          "percent":"20%",
          "flow":"50KB"
        },
        {
          "receiveIP":"192.2.15.161",
          "percent":"20%",
          "flow":"50KB"
        },
        {
          "receiveIP":"192.2.15.161",
          "percent":"20%",
          "flow":"50KB"
        },
        {
          "receiveIP":"192.2.15.161",
          "percent":"20%",
          "flow":"50KB"
        },
        {
          "receiveIP":"192.2.15.161",
          "percent":"20%",
          "flow":"50KB"
        },
        {
          "receiveIP":"192.2.15.161",
          "percent":"20%",
          "flow":"50KB"
        }
      ],
      "appProto": [
        {
          "appProto":"HTTP",
          "percent":"20%",
          "flow":"50KB"
        },
        {
          "appProto":"HTTP",
          "percent":"20%",
          "flow":"50KB"
        },
        {
          "appProto":"HTTP",
          "percent":"20%",
          "flow":"50KB"
        },
        {
          "appProto":"HTTP",
          "percent":"20%",
          "flow":"50KB"
        },
        {
          "appProto":"HTTP",
          "percent":"20%",
          "flow":"50KB"
        },
        {
          "appProto":"HTTP",
          "percent":"20%",
          "flow":"50KB"
        },
        {
          "appProto":"HTTP",
          "percent":"20%",
          "flow":"50KB"
        },
        {
          "appProto":"HTTP",
          "percent":"20%",
          "flow":"50KB"
        }
      ],
      "tranProto": [
        {
          "tranProto":"HTTP",
          "percent":"20%",
          "flow":"50KB"
        },
        {
          "tranProto":"HTTP",
          "percent":"20%",
          "flow":"50KB"
        },
        {
          "tranProto":"HTTP",
          "percent":"20%",
          "flow":"50KB"
        },
        {
          "tranProto":"HTTP",
          "percent":"20%",
          "flow":"50KB"
        },
        {
          "tranProto":"HTTP",
          "percent":"20%",
          "flow":"50KB"
        },
        {
          "tranProto":"HTTP",
          "percent":"20%",
          "flow":"50KB"
        },
        {
          "tranProto":"HTTP",
          "percent":"20%",
          "flow":"50KB"
        },
        {
          "tranProto":"HTTP",
          "percent":"20%",
          "flow":"50KB"
        }
      ]
    },
    "vulne": {

    }
  }
}
